src/__init__.py
src/basin_entropy.py
basin_entropy-0.0.1.dist-info/METADATA
basin_entropy-0.0.1.dist-info/WHEEL
basin_entropy-0.0.1.dist-info/top_level.txt
basin_entropy-0.0.1.dist-info/RECORD
