Metadata-Version: 2.1
Name: basin-entropy
Version: 0.0.1
Summary: Script to calculate basin entropy
Home-page: UNKNOWN
Author: Oliveira, Jonas
Author-email: <jonasferoliveira.ufg@gmail.com>
License: UNKNOWN
Keywords: python,basins,entropy,fractals
Platform: UNKNOWN
Classifier: Development Status :: 1 - Planning
Classifier: Intended Audience :: Developers
Classifier: Programming Language :: Python :: 3
Classifier: Operating System :: Unix
Classifier: Operating System :: MacOS :: MacOS X
Classifier: Operating System :: Microsoft :: Windows
Requires-Dist: numpy
